glennbotlist/GBL.py
glennbotlist/WebhookServer.py
glennbotlist/__init__.py
glennbotlist/bot.py
glennbotlist/errors.py
glennbotlist/user.py
gblpyapi-0.3.1.dist-info/LICENSE
gblpyapi-0.3.1.dist-info/METADATA
gblpyapi-0.3.1.dist-info/WHEEL
gblpyapi-0.3.1.dist-info/top_level.txt
gblpyapi-0.3.1.dist-info/RECORD
