Metadata-Version: 2.1
Name: gblpyapi
Version: 0.3.1
Summary: glennbotlist.xyz API Wrapper in Python
Home-page: https://glennbotlist.xyz
Author: A Trash Coder
Author-email: gavynlamar@gmail.com
License: MIT
Platform: UNKNOWN
Classifier: Programming Language :: Python :: 3
Classifier: Operating System :: OS Independent
Requires-Dist: aiohttp
